<?xml version="1.0" encoding="UTF-8" standalone="no" ?>
<!--
Derived from The LDraw Parts Library
Orginal Author: Philippe Hurbain [Philo]
Edited for LDD by Equilibrium
-->
<LEGOPrimitive versionMajor="1" versionMinor="0">
  <Annotations>
    <Annotation aliases="41041"/>
    <Annotation designname="POWERED UP XL-MOTOR Back"/>
    <Annotation maingroupid="399"/>
    <Annotation maingroupname="LOOSE PARTS"/>
    <Annotation platformid="300"/>
    <Annotation platformname="TECHNIC"/>
    <Annotation version="13"/>
  </Annotations>
  <Collision>
	  <Box sX="0.978416" sY="0.02" sZ="0.31" angle="180.0" ax="-0.707107" ay="-0.707107" az="0.0" tx="-4.52" ty="0.803416" tz="-2.8"/>
	  <Box sX="0.978416" sY="0.02" sZ="0.31" angle="180.0" ax="-0.707107" ay="-0.707107" az="0.0" tx="-5.08" ty="0.803416" tz="-2.8"/>
	  <Box sX="0.0055" sY="0.097949" sZ="0.389886" angle="180.0" ax="-0.906308" ay="-0.422618" az="0.0" tx="-5.00923" ty="-0.249347" tz="-2.79989"/>
	  <Box sX="0.0055" sY="0.097949" sZ="0.389886" angle="180.0" ax="-0.422618" ay="-0.906308" az="0.0" tx="-4.59077" ty="-0.249347" tz="-2.79989"/>
	  <Box sX="0.0055" sY="0.097949" sZ="0.389886" angle="180.0" ax="-0.707107" ay="-0.707107" az="0.0" tx="-4.8" ty="-0.3255" tz="-2.79989"/>
	  <Box sX="0.0055" sY="0.097949" sZ="0.39" angle="50.0001" ax="2.37403e-007" ay="0.0" az="-1.0" tx="-5.00923" ty="1.84935" tz="-2.8"/>
	  <Box sX="0.0055" sY="0.097949" sZ="0.39" angle="130.0" ax="-3.42035e-007" ay="6.19375e-007" az="-1.0" tx="-4.59077" ty="1.84935" tz="-2.8"/>
	  <Box sX="0.0055" sY="0.097949" sZ="0.39" angle="90.0" ax="0.0" ay="0.0" az="-1.0" tx="-4.8" ty="1.9255" tz="-2.8"/>
	  <Box sX="0.359" sY="0.39" sZ="0.08" angle="180.0" ax="0.0" ay="-0.707107" az="-0.707107" tx="-4.8015" ty="1.2" tz="-2.8"/>
	  <Box sX="0.359" sY="0.39" sZ="0.08" angle="180.0" ax="0.0" ay="-0.707107" az="-0.707107" tx="-4.8015" ty="0.4" tz="-2.8"/>
	  <Box sX="0.79" sY="0.39" sZ="0.0195" angle="120.0" ax="0.57735" ay="-0.57735" az="-0.57735" tx="-5.1415" ty="0.8" tz="-2.8"/>
	  <Box sX="0.79" sY="0.39" sZ="0.019" angle="120.0" ax="0.57735" ay="-0.57735" az="-0.577351" tx="-4.461" ty="0.8" tz="-2.8"/>
	  <Box sX="0.978416" sY="0.02" sZ="0.31" angle="180.0" ax="-0.707107" ay="-0.707107" az="0.0" tx="-4.52" ty="0.803416" tz="0.4"/>
	  <Box sX="0.978416" sY="0.02" sZ="0.31" angle="180.0" ax="-0.707107" ay="-0.707107" az="0.0" tx="-5.08" ty="0.803416" tz="0.4"/>
	  <Box sX="0.0055" sY="0.097949" sZ="0.389886" angle="180.0" ax="-0.906308" ay="-0.422618" az="0.0" tx="-5.00923" ty="-0.249347" tz="0.400114"/>
	  <Box sX="0.0055" sY="0.097949" sZ="0.389886" angle="180.0" ax="-0.422618" ay="-0.906308" az="0.0" tx="-4.59077" ty="-0.249347" tz="0.400114"/>
	  <Box sX="0.0055" sY="0.097949" sZ="0.389886" angle="180.0" ax="-0.707107" ay="-0.707107" az="0.0" tx="-4.8" ty="-0.3255" tz="0.400114"/>
	  <Box sX="0.0055" sY="0.097949" sZ="0.39" angle="50.0001" ax="2.37403e-007" ay="0.0" az="-1.0" tx="-5.00923" ty="1.84935" tz="0.4"/>
	  <Box sX="0.0055" sY="0.097949" sZ="0.39" angle="130.0" ax="-3.42035e-007" ay="6.19375e-007" az="-1.0" tx="-4.59077" ty="1.84935" tz="0.4"/>
	  <Box sX="0.0055" sY="0.097949" sZ="0.39" angle="90.0" ax="0.0" ay="0.0" az="-1.0" tx="-4.8" ty="1.9255" tz="0.4"/>
	  <Box sX="0.359" sY="0.39" sZ="0.08" angle="180.0" ax="0.0" ay="-0.707107" az="-0.707107" tx="-4.79564" ty="1.2" tz="0.4"/>
	  <Box sX="0.359" sY="0.39" sZ="0.08" angle="180.0" ax="0.0" ay="-0.707107" az="-0.707107" tx="-4.79564" ty="0.4" tz="0.4"/>
	  <Box sX="0.79" sY="0.39" sZ="0.0195" angle="120.0" ax="0.57735" ay="-0.57735" az="-0.57735" tx="-5.13564" ty="0.8" tz="0.4"/>
	  <Box sX="0.79" sY="0.39" sZ="0.019" angle="120.0" ax="0.57735" ay="-0.57735" az="-0.577351" tx="-4.461" ty="0.8" tz="0.4"/>
	  <Box sX="1.22" sY="1.152" sZ="1.95193" angle="180.0" ax="-1.0" ay="-1.50996e-007" az="0.0" tx="-3.229" ty="0.8" tz="-1.2"/>
	  <Box sX="0.0055" sY="0.16419" sZ="0.39" angle="90.0" ax="2.38419e-007" ay="-2.38419e-007" az="-1.0" tx="-5.32828" ty="1.92522" tz="-0.4"/>
	  <Box sX="0.0055" sY="0.16419" sZ="0.39" angle="90.0" ax="2.38419e-007" ay="-2.38419e-007" az="-1.0" tx="-5.32828" ty="1.92522" tz="-2.0"/>
	  <Box sX="0.0055" sY="0.16132" sZ="0.39" angle="180.0" ax="-0.707107" ay="-0.707107" az="0.0" tx="-5.32499" ty="-0.325783" tz="-2.0"/>
	  <Box sX="0.0055" sY="0.16132" sZ="0.39" angle="180.0" ax="-0.707107" ay="-0.707107" az="0.0" tx="-5.32499" ty="-0.325783" tz="-0.4"/>
	  <Box sX="0.479999" sY="0.353274" sZ="0.035311" angle="180.0" ax="-0.707107" ay="-0.707107" az="0.0" tx="-5.59972" ty="0.799307" tz="-0.755"/>
	  <Box sX="0.479999" sY="0.352377" sZ="0.035311" angle="180.0" ax="-0.707107" ay="-0.707107" az="0.0" tx="-5.59972" ty="0.799307" tz="-0.0450001"/>
	  <Box sX="0.239753" sY="0.39" sZ="0.0195" angle="120.0" ax="0.57735" ay="-0.57735" az="-0.57735" tx="-5.93639" ty="0.244717" tz="-0.4"/>
	  <Box sX="0.34669" sY="0.39" sZ="0.08" angle="180.0" ax="0.0" ay="-0.707107" az="-0.707107" tx="-5.60122" ty="0.399717" tz="-0.4"/>
	  <Box sX="0.34669" sY="0.39" sZ="0.08" angle="180.0" ax="0.0" ay="-0.707107" az="-0.707107" tx="-5.60122" ty="1.19972" tz="-0.4"/>
	  <Box sX="0.0055" sY="0.097949" sZ="0.39" angle="90.0" ax="2.38419e-007" ay="-2.38419e-007" az="-1.0" tx="-5.59972" ty="1.92522" tz="-0.4"/>
	  <Box sX="0.0055" sY="0.097949" sZ="0.39" angle="130.0" ax="-3.49595e-007" ay="1.27242e-007" az="-1.0" tx="-5.39049" ty="1.84907" tz="-0.4"/>
	  <Box sX="0.0055" sY="0.097949" sZ="0.39" angle="50.0" ax="1.07111e-006" ay="-3.72766e-007" az="-1.0" tx="-5.80894" ty="1.84907" tz="-0.4"/>
	  <Box sX="0.0055" sY="0.097949" sZ="0.39" angle="180.0" ax="-0.707107" ay="-0.707107" az="0.0" tx="-5.59972" ty="-0.325783" tz="-0.4"/>
	  <Box sX="0.0055" sY="0.097949" sZ="0.389886" angle="180.0" ax="-0.422618" ay="-0.906308" az="0.0" tx="-5.39049" ty="-0.24963" tz="-0.39989"/>
	  <Box sX="0.0055" sY="0.097949" sZ="0.389886" angle="180.0" ax="-0.906308" ay="-0.422618" az="0.0" tx="-5.80894" ty="-0.24963" tz="-0.39989"/>
	  <Box sX="0.34669" sY="0.39" sZ="0.08" angle="180.0" ax="0.0" ay="-0.707107" az="-0.707107" tx="-5.60122" ty="0.399717" tz="-2.0"/>
	  <Box sX="0.34669" sY="0.39" sZ="0.08" angle="180.0" ax="0.0" ay="-0.707107" az="-0.707107" tx="-5.60122" ty="1.19972" tz="-2.0"/>
	  <Box sX="0.0055" sY="0.097949" sZ="0.39" angle="90.0" ax="0.0" ay="0.0" az="-1.0" tx="-5.59972" ty="1.92522" tz="-2.0"/>
	  <Box sX="0.0055" sY="0.097949" sZ="0.39" angle="130.0" ax="-3.49595e-007" ay="1.27242e-007" az="-1.0" tx="-5.39049" ty="1.84907" tz="-2.0"/>
	  <Box sX="0.0055" sY="0.097949" sZ="0.39" angle="50.0" ax="1.07111e-006" ay="-3.72766e-007" az="-1.0" tx="-5.80894" ty="1.84907" tz="-2.0"/>
	  <Box sX="0.0055" sY="0.097949" sZ="0.39" angle="180.0" ax="-0.707107" ay="-0.707107" az="0.0" tx="-5.59972" ty="-0.325783" tz="-2.0"/>
	  <Box sX="0.0055" sY="0.097949" sZ="0.389886" angle="180.0" ax="-0.422618" ay="-0.906308" az="0.0" tx="-5.39049" ty="-0.24963" tz="-1.99989"/>
	  <Box sX="0.0055" sY="0.097949" sZ="0.389886" angle="180.0" ax="-0.906308" ay="-0.422618" az="0.0" tx="-5.80894" ty="-0.24963" tz="-1.99989"/>
	  <Box sX="0.235087" sY="0.39" sZ="0.0195" angle="120.0" ax="0.57735" ay="-0.57735" az="-0.57735" tx="-5.93639" ty="0.244717" tz="-2.0"/>
	  <Box sX="0.240626" sY="0.39" sZ="0.0195" angle="120.0" ax="0.57735" ay="-0.57735" az="-0.57735" tx="-5.93639" ty="1.35972" tz="-2.0"/>
	  <Box sX="0.240626" sY="0.39" sZ="0.0195" angle="120.0" ax="0.57735" ay="-0.57735" az="-0.57735" tx="-5.93639" ty="1.35972" tz="-0.4"/>
	  <Box sX="0.240626" sY="0.39" sZ="0.0195" angle="120.0" ax="0.57735" ay="-0.57735" az="-0.57735" tx="-5.26322" ty="1.35972" tz="-2.0"/>
	  <Box sX="0.235087" sY="0.39" sZ="0.0195" angle="120.0" ax="0.57735" ay="-0.57735" az="-0.57735" tx="-5.26322" ty="0.244717" tz="-2.0"/>
	  <Box sX="0.239753" sY="0.39" sZ="0.0195" angle="120.0" ax="0.57735" ay="-0.57735" az="-0.57735" tx="-5.26322" ty="0.244717" tz="-0.4"/>
	  <Box sX="0.240626" sY="0.39" sZ="0.0195" angle="120.0" ax="0.57735" ay="-0.57735" az="-0.57735" tx="-5.26322" ty="1.35972" tz="-0.4"/>
	  <Box sX="0.339325" sY="0.02" sZ="0.31" angle="180.0" ax="-0.707107" ay="-0.707107" az="0.0" tx="-5.31972" ty="1.43972" tz="-0.4"/>
	  <Box sX="0.339325" sY="0.02" sZ="0.31" angle="180.0" ax="-0.707107" ay="-0.707107" az="0.0" tx="-5.31972" ty="1.43972" tz="-2.0"/>
	  <Box sX="0.339761" sY="0.02" sZ="0.31" angle="180.0" ax="-0.707107" ay="-0.707107" az="0.0" tx="-5.31972" ty="0.155717" tz="-0.4"/>
	  <Box sX="0.339761" sY="0.02" sZ="0.31" angle="180.0" ax="-0.707107" ay="-0.707107" az="0.0" tx="-5.31972" ty="0.155717" tz="-2.0"/>
	  <Box sX="0.339325" sY="0.02" sZ="0.31" angle="180.0" ax="-0.707107" ay="-0.707107" az="0.0" tx="-5.87972" ty="1.43972" tz="-2.0"/>
	  <Box sX="0.339761" sY="0.02" sZ="0.31" angle="180.0" ax="-0.707107" ay="-0.707107" az="0.0" tx="-5.87972" ty="0.155717" tz="-2.0"/>
	  <Box sX="0.339761" sY="0.02" sZ="0.31" angle="180.0" ax="-0.707107" ay="-0.707107" az="0.0" tx="-5.87972" ty="0.155717" tz="-0.4"/>
	  <Box sX="0.339325" sY="0.02" sZ="0.31" angle="180.0" ax="-0.707107" ay="-0.707107" az="0.0" tx="-5.87972" ty="1.43972" tz="-0.4"/>
	  <Box sX="0.479999" sY="0.351787" sZ="0.035311" angle="180.0" ax="-0.707107" ay="-0.707107" az="0.0" tx="-5.59972" ty="0.799307" tz="-2.355"/>
	  <Box sX="0.479999" sY="0.353274" sZ="0.035311" angle="180.0" ax="-0.707107" ay="-0.707107" az="0.0" tx="-5.59972" ty="0.799307" tz="-1.645"/>
	  <Box sX="0.775" sY="1.152" sZ="1.19518" angle="180.0" ax="-1.0" ay="-1.50996e-007" az="0.0" tx="-4.38" ty="0.8" tz="-1.2"/>
	  <Box sX="0.0055" sY="0.097949" sZ="1.19" angle="90.0" ax="0.0" ay="0.0" az="-1.0" tx="-4.79579" ty="2.73074" tz="-1.2"/>
	  <Box sX="0.0055" sY="0.097949" sZ="1.19" angle="50.0001" ax="1.07111e-006" ay="-3.72767e-007" az="-1.0" tx="-5.00502" ty="2.65459" tz="-1.2"/>
	  <Box sX="0.0055" sY="0.127796" sZ="1.14864" angle="90.0" ax="0.0" ay="0.0" az="-1.0" tx="-4.5468" ty="2.73074" tz="-1.2"/>
	  <Box sX="0.339325" sY="0.02" sZ="1.10605" angle="180.0" ax="-0.707107" ay="-0.707107" az="0.0" tx="-5.07579" ty="2.24524" tz="-1.2"/>
	  <Box sX="0.240626" sY="1.19" sZ="0.0195" angle="120.0" ax="0.57735" ay="-0.57735" az="-0.57735" tx="-5.13729" ty="2.16524" tz="-1.2"/>
	  <Box sX="0.375831" sY="0.02" sZ="1.10605" angle="180.0" ax="-0.707107" ay="-0.707107" az="0.0" tx="-4.52162" ty="2.33619" tz="-1.2"/>
	  <Box sX="0.201058" sY="1.94905" sZ="0.395722" angle="180.0" ax="-1.0" ay="-1.50996e-007" az="0.0" tx="-4.606" ty="0.8" tz="-1.2"/>
	  <Box sX="0.34846" sY="0.0446593" sZ="1.19052" angle="180.0" ax="-1.0" ay="-1.50996e-007" az="0.0" tx="-4.8" ty="2.01448" tz="-1.2"/>
	  <Box sX="0.0055" sY="0.097949" sZ="1.19" angle="180.0" ax="-0.707107" ay="-0.707107" az="0.0" tx="-4.796" ty="-1.1304" tz="-1.2"/>
	  <Box sX="0.0055" sY="0.1278" sZ="1.14864" angle="180.0" ax="-0.707107" ay="-0.707107" az="0.0" tx="-4.547" ty="-1.1304" tz="-1.2"/>
	  <Box sX="0.0055" sY="0.097949" sZ="1.19" angle="180.0" ax="-0.906308" ay="-0.422618" az="0.0" tx="-5.005" ty="-1.05424" tz="-1.2"/>
	  <Box sX="0.381344" sY="0.02" sZ="1.10605" angle="180.0" ax="-0.707107" ay="-0.707107" az="0.0" tx="-4.522" ty="-0.736102" tz="-1.2"/>
	  <Box sX="0.339761" sY="0.02" sZ="1.10605" angle="180.0" ax="-0.707107" ay="-0.707107" az="0.0" tx="-5.076" ty="-0.648895" tz="-1.2"/>
	  <Box sX="0.235087" sY="1.19" sZ="0.0195" angle="120.0" ax="0.57735" ay="-0.57735" az="-0.57735" tx="-5.137" ty="-0.559895" tz="-1.2"/>
	  <Box sX="0.34846" sY="0.0446593" sZ="1.19052" angle="180.0" ax="-1.0" ay="-1.50996e-007" az="0.0" tx="-4.8" ty="-0.413656" tz="-1.2"/>
	  <Box sX="1.22" sY="1.95" sZ="1.15" angle="180.0" ax="-1.0" ay="-1.50996e-007" az="0.0" tx="-3.22919" ty="0.8" tz="-1.2"/>
  </Collision>
  <Connectivity>
	  <Axel type="2" length="0.8" grabbing="0" startCapped="0" endCapped="0" angle="240.0" ax="-0.57735" ay="-0.57735" az="-0.57735" tx="-4.8" ty="1.6" tz="-3.2"/>
	  <Axel type="2" length="0.8" grabbing="0" startCapped="0" endCapped="0" angle="240.0" ax="-0.57735" ay="-0.57735" az="-0.57735" tx="-4.8" ty="0.0" tz="-3.2"/>
	  <Axel type="2" length="0.8" grabbing="0" startCapped="0" endCapped="0" angle="120.0" ax="-0.57735" ay="-0.57735" az="0.57735" tx="-4.8" ty="1.6" tz="0.8"/>
	  <Axel type="2" length="0.8" grabbing="0" startCapped="0" endCapped="0" angle="120.0" ax="-0.57735" ay="-0.57735" az="0.57735" tx="-4.8" ty="0.0" tz="0.8"/>
	  <Axel type="2" length="0.8" grabbing="0" startCapped="0" endCapped="0" angle="120.0" ax="-0.57735" ay="-0.57735" az="0.57735" tx="-4.8" ty="-0.8" tz="0.0"/>
	  <Axel type="2" length="0.8" grabbing="0" startCapped="0" endCapped="0" angle="240.0" ax="-0.57735" ay="-0.57735" az="-0.57735" tx="-4.8" ty="-0.8" tz="-2.4"/>
	  <Axel type="2" length="0.8" grabbing="0" startCapped="0" endCapped="0" angle="120.0" ax="-0.57735" ay="-0.57735" az="0.57735" tx="-4.8" ty="2.4" tz="0.0"/>
	  <Axel type="2" length="0.8" grabbing="0" startCapped="0" endCapped="0" angle="240.0" ax="-0.57735" ay="-0.57735" az="-0.57735" tx="-4.8" ty="2.4" tz="-2.4"/>
	  <Axel type="2" length="0.8" grabbing="0" startCapped="0" endCapped="0" angle="240.0" ax="-0.57735" ay="-0.57735" az="-0.57735" tx="-4.8" ty="0.8" tz="-3.2"/>
	  <Axel type="2" length="0.8" grabbing="0" startCapped="0" endCapped="0" angle="120.0" ax="-0.57735" ay="-0.57735" az="0.57735" tx="-4.8" ty="0.8" tz="0.8"/>
	  <Axel type="2" length="0.8" grabbing="0" startCapped="0" endCapped="0" angle="120.0" ax="-0.57735" ay="0.57735" az="-0.57735" tx="-5.6" ty="0.0" tz="0.0"/>
	  <Axel type="2" length="0.8" grabbing="0" startCapped="0" endCapped="0" angle="120.0" ax="-0.57735" ay="0.57735" az="-0.57735" tx="-5.6" ty="1.6" tz="0.0"/>
	  <Axel type="2" length="0.8" grabbing="0" startCapped="0" endCapped="0" angle="90.0" ax="0.0" ay="0.0" az="-1.0" tx="-6.0" ty="0.8" tz="-2.0"/>
	  <Axel type="2" length="0.8" grabbing="0" startCapped="0" endCapped="0" angle="90.0" ax="0.0" ay="0.0" az="-1.0" tx="-6.0" ty="0.8" tz="-0.4"/>
	  <Axel type="2" length="0.8" grabbing="0" startCapped="0" endCapped="0" angle="240.0" ax="-0.57735" ay="0.57735" az="0.57735" tx="-5.6" ty="0.0" tz="-2.4"/>
	  <Axel type="2" length="0.8" grabbing="0" startCapped="0" endCapped="0" angle="240.0" ax="-0.57735" ay="0.57735" az="0.57735" tx="-5.6" ty="1.6" tz="-2.4"/>
		<Fixed type="3" axes="2" angle="180.0" ax="-1.0" ay="0.0" az="0.0" tx="-2.0" ty="0.8" tz="-1.2"/>
		<Fixed type="2" axes="2" angle="180.0" ax="-1.0" ay="0.0" az="0.0" tx="-5.08" ty="0.800001" tz="-1.2"/>
		<Fixed type="2" axes="2" angle="1.10662e-005" ax="0.0" ay="0.0" az="0.0" tx="-5.6" ty="0.800001" tz="-1.2"/>
  </Connectivity>
  <PhysicsAttributes inertiaTensor="54.23239,0,0,0,182.57419,0,0,0,203.99773" centerOfMass="-3.99962,0.800057,-1.19963" mass="18.5" frictionType="0"/>
  <Bounding>
    <AABB minX="-5.99962" minY="-1.15994" minZ="-3.19963" maxX="-1.99962" maxY="2.76006" maxZ="0.800375"/>
  </Bounding>
  <GeometryBounding>
    <AABB minX="-5.99962" minY="-1.15994" minZ="-3.19963" maxX="-1.99962" maxY="2.76006" maxZ="0.800375"/>
  </GeometryBounding>
</LEGOPrimitive>
