<?xml version="1.0" encoding="utf-8" standalone="no"?>
<!--
	Derived from: LDraw Parts Library
	Orginal Author: Jens Brühl [jb70]
	Editted for LDD by: Stephan
	Last modification: 2022-07-27
	Comments: v0.0: Initial release [Stephan] 2022-07-27.
-->
<LEGOPrimitive versionMajor="1" versionMinor="0">
  <Annotations>
    <Annotation aliases="80278" />
    <Annotation designname="LEFT PANEL 5X4" />
    <Annotation maingroupid="312" />
    <Annotation maingroupname="BEAMS W/ SHAPES" />
    <Annotation platformid="300" />
    <Annotation platformname="TECHNIC" />
    <Annotation version="2" />
  </Annotations>
  <Collision>
    <Box sX="0.010789" sY="0.114266" sZ="0.352036" angle="180" ax="0.1951" ay="0.9808" az="0" tx="0.0952" ty="0.5266" tz="1.1597" />
    <Box sX="0.010789" sY="0.114266" sZ="0.352036" angle="112.5" ax="0" ay="0" az="1" tx="0.2734" ty="0.7057" tz="1.1597" />
    <Box sX="0.010789" sY="0.114266" sZ="0.39" angle="180" ax="0.9808" ay="-0.1951" az="0" tx="0.7051" ty="0.2734" tz="1.1196" />
    <Box sX="0.010789" sY="0.114266" sZ="0.352036" angle="67.5" ax="0" ay="0" az="-1" tx="0.5266" ty="0.0943" tz="1.1597" />
    <Box sX="0.010789" sY="0.114266" sZ="0.352036" angle="67.5" ax="0" ay="0" az="1" tx="0.5266" ty="0.7057" tz="1.1597" />
    <Box sX="0.010789" sY="0.114266" sZ="0.352036" angle="180" ax="-0.1951" ay="0.9808" az="0" tx="0.0952" ty="0.2734" tz="1.1597" />
    <Box sX="0.010789" sY="0.114266" sZ="0.39" angle="180" ax="0.8315" ay="-0.5556" az="0" tx="0.5267" ty="0.0928" tz="1.1196" />
    <Box sX="0.010789" sY="0.114266" sZ="0.39" angle="180" ax="0.9808" ay="0.1951" az="0" tx="0.7051" ty="0.5266" tz="1.1196" />
    <Box sX="0.196626" sY="0.02" sZ="0.31" angle="0" ax="1" ay="0" az="0" tx="0.4047" ty="0.12" tz="1.1196" />
    <Box sX="0.196626" sY="0.02" sZ="0.31" angle="0" ax="1" ay="0" az="0" tx="0.4216" ty="0.68" tz="1.1196" />
    <Box sX="0.010789" sY="0.114266" sZ="0.352036" angle="180" ax="0.1951" ay="0.9808" az="0" tx="-0.7083" ty="3.7266" tz="1.1597" />
    <Box sX="0.010789" sY="0.114266" sZ="0.352036" angle="112.5" ax="0" ay="0" az="1" tx="-0.5276" ty="3.9057" tz="1.1597" />
    <Box sX="0.010789" sY="0.114266" sZ="0.39" angle="180" ax="0.9808" ay="-0.1951" az="0" tx="-0.0932" ty="3.4734" tz="1.1196" />
    <Box sX="0.010789" sY="0.114266" sZ="0.352036" angle="67.5" ax="0" ay="0" az="-1" tx="-0.2744" ty="3.2943" tz="1.1597" />
    <Box sX="0.010789" sY="0.114266" sZ="0.352036" angle="67.5" ax="0" ay="0" az="1" tx="-0.2744" ty="3.9057" tz="1.1597" />
    <Box sX="0.010789" sY="0.114266" sZ="0.352036" angle="180" ax="-0.1951" ay="0.9808" az="0" tx="-0.7083" ty="3.4734" tz="1.1597" />
    <Box sX="0.010789" sY="0.114266" sZ="0.39" angle="180" ax="0.8315" ay="-0.5556" az="0" tx="-0.2723" ty="3.2943" tz="1.1196" />
    <Box sX="0.010789" sY="0.114266" sZ="0.39" angle="180" ax="0.9808" ay="0.1951" az="0" tx="-0.0819" ty="3.6993" tz="1.1196" />
    <Box sX="0.196626" sY="0.02" sZ="0.31" angle="0" ax="1" ay="0" az="0" tx="-0.3794" ty="3.32" tz="1.1196" />
    <Box sX="0.196626" sY="0.02" sZ="0.31" angle="0" ax="1" ay="0" az="0" tx="-0.3992" ty="3.88" tz="1.1196" />
    <Box sX="0.35705" sY="0.02" sZ="0.372149" angle="90" ax="0" ay="0" az="1" tx="0.0661" ty="0.3576" tz="-0.0804" />
    <Box sX="0.35705" sY="0.346901" sZ="0.076035" angle="90" ax="0" ay="0" az="1" tx="0.3954" ty="0.3576" tz="-0.0804" />
    <Box sX="0.35705" sY="0.113383" sZ="0.016858" angle="90" ax="0" ay="0" az="1" tx="0.5168" ty="0.3576" tz="-0.8186" />
    <Box sX="0.35705" sY="0.070048" sZ="0.010611" angle="90" ax="0" ay="0" az="1" tx="0.4034" ty="0.3576" tz="-0.8152" />
    <Box sX="0.190717" sY="0.016261" sZ="0.743977" angle="90" ax="0" ay="0" az="1" tx="0.737" ty="0.2074" tz="-0.4695" />
    <Box sX="0.35705" sY="0.070048" sZ="0.010611" angle="120" ax="0.5774" ay="0.5774" az="0.5774" tx="0.7338" ty="0.3576" tz="-0.4791" />
    <Box sX="0.35705" sY="0.070048" sZ="0.010611" angle="120" ax="0.5774" ay="0.5774" az="0.5774" tx="0.0673" ty="0.3576" tz="-0.4791" />
    <Box sX="0.35705" sY="0.070048" sZ="0.010611" angle="132.1486" ax="0.6337" ay="0.6337" az="0.4437" tx="0.7155" ty="0.3576" tz="-0.594" />
    <Box sX="0.35705" sY="0.070048" sZ="0.010611" angle="132.1486" ax="0.6337" ay="0.6337" az="0.4437" tx="0.0875" ty="0.3576" tz="-0.3641" />
    <Box sX="0.35705" sY="0.070048" sZ="0.010611" angle="148.602" ax="0.6786" ay="0.6786" az="0.2811" tx="0.641" ty="0.3576" tz="-0.7167" />
    <Box sX="0.35705" sY="0.070048" sZ="0.010611" angle="148.602" ax="0.6786" ay="0.6786" az="0.2811" tx="0.1657" ty="0.3576" tz="-0.2414" />
    <Box sX="0.35705" sY="0.070048" sZ="0.010611" angle="165.8932" ax="0.7017" ay="0.7017" az="0.1237" tx="0.5183" ty="0.3576" tz="-0.7949" />
    <Box sX="0.35705" sY="0.070048" sZ="0.010611" angle="165.8932" ax="0.7017" ay="0.7017" az="0.1237" tx="0.2884" ty="0.3576" tz="-0.1633" />
    <Box sX="0.35705" sY="0.070048" sZ="0.010611" angle="162.3962" ax="-0.6986" ay="-0.6986" az="0.1548" tx="0.2613" ty="0.3576" tz="-0.7837" />
    <Box sX="0.35705" sY="0.070048" sZ="0.010611" angle="162.3962" ax="-0.6986" ay="-0.6986" az="0.1548" tx="0.5454" ty="0.3576" tz="-0.1745" />
    <Box sX="0.35705" sY="0.070048" sZ="0.010611" angle="148.602" ax="-0.6786" ay="-0.6786" az="0.2811" tx="0.1657" ty="0.3576" tz="-0.7167" />
    <Box sX="0.35705" sY="0.070048" sZ="0.010611" angle="148.602" ax="-0.6786" ay="-0.6786" az="0.2811" tx="0.641" ty="0.3576" tz="-0.2414" />
    <Box sX="0.35705" sY="0.070048" sZ="0.010611" angle="132.1486" ax="-0.6337" ay="-0.6337" az="0.4437" tx="0.0875" ty="0.3576" tz="-0.594" />
    <Box sX="0.35705" sY="0.070048" sZ="0.010611" angle="132.1486" ax="-0.6337" ay="-0.6337" az="0.4437" tx="0.7117" ty="0.3576" tz="-0.3641" />
    <Box sX="0.35705" sY="0.070048" sZ="0.010611" angle="90" ax="0" ay="0" az="1" tx="0.4034" ty="0.3576" tz="0.657" />
    <Box sX="0.35705" sY="0.070048" sZ="0.010611" angle="120" ax="0.5774" ay="0.5774" az="0.5774" tx="0.734" ty="0.3576" tz="0.3022" />
    <Box sX="0.35705" sY="0.070048" sZ="0.010611" angle="120" ax="0.5774" ay="0.5774" az="0.5774" tx="0.0673" ty="0.3576" tz="0.3209" />
    <Box sX="0.35705" sY="0.070048" sZ="0.010611" angle="132.1486" ax="0.6337" ay="0.6337" az="0.4437" tx="0.7107" ty="0.3576" tz="0.2063" />
    <Box sX="0.35705" sY="0.070048" sZ="0.010611" angle="132.1486" ax="0.6337" ay="0.6337" az="0.4437" tx="0.0875" ty="0.3576" tz="0.4359" />
    <Box sX="0.35705" sY="0.070048" sZ="0.010611" angle="148.602" ax="0.6786" ay="0.6786" az="0.2811" tx="0.641" ty="0.3576" tz="0.0833" />
    <Box sX="0.35705" sY="0.070048" sZ="0.010611" angle="148.602" ax="0.6786" ay="0.6786" az="0.2811" tx="0.1657" ty="0.3576" tz="0.5586" />
    <Box sX="0.35705" sY="0.070048" sZ="0.010611" angle="165.8932" ax="0.7017" ay="0.7017" az="0.1237" tx="0.5183" ty="0.3576" tz="0.0051" />
    <Box sX="0.35705" sY="0.070048" sZ="0.010611" angle="165.8932" ax="0.7017" ay="0.7017" az="0.1237" tx="0.2884" ty="0.3576" tz="0.6367" />
    <Box sX="0.35705" sY="0.070048" sZ="0.010611" angle="162.3962" ax="-0.6986" ay="-0.6986" az="0.1548" tx="0.2613" ty="0.3576" tz="0.0163" />
    <Box sX="0.35705" sY="0.070048" sZ="0.010611" angle="162.3962" ax="-0.6986" ay="-0.6986" az="0.1548" tx="0.5454" ty="0.3576" tz="0.6255" />
    <Box sX="0.35705" sY="0.070048" sZ="0.010611" angle="148.602" ax="-0.6786" ay="-0.6786" az="0.2811" tx="0.1657" ty="0.3576" tz="0.0833" />
    <Box sX="0.35705" sY="0.070048" sZ="0.010611" angle="148.602" ax="-0.6786" ay="-0.6786" az="0.2811" tx="0.641" ty="0.3576" tz="0.5586" />
    <Box sX="0.35705" sY="0.070048" sZ="0.010611" angle="132.1486" ax="-0.6337" ay="-0.6337" az="0.4437" tx="0.0875" ty="0.3576" tz="0.206" />
    <Box sX="0.35705" sY="0.070048" sZ="0.010611" angle="132.1486" ax="-0.6337" ay="-0.6337" az="0.4437" tx="0.7131" ty="0.3576" tz="0.4359" />
    <Box sX="0.018226" sY="0.034995" sZ="0.512487" angle="90" ax="0" ay="0" az="1" tx="0.6039" ty="0.8212" tz="-0.0806" />
    <Box sX="0.279669" sY="0.022363" sZ="1.272135" angle="92.3903" ax="0" ay="0" az="1" tx="0.7209" ty="0.724" tz="0.2089" />
    <Box sX="0.279669" sY="0.0251" sZ="1.058902" angle="96.7291" ax="0" ay="0" az="1" tx="0.6606" ty="1.3095" tz="0.4518" />
    <Box sX="0.279669" sY="0.0251" sZ="0.830086" angle="101.5333" ax="0" ay="0" az="1" tx="0.5573" ty="1.8964" tz="0.6761" />
    <Box sX="0.279669" sY="0.0251" sZ="0.608863" angle="106.1617" ax="0" ay="0" az="1" tx="0.422" ty="2.4822" tz="0.8858" />
    <Box sX="0.279669" sY="0.0251" sZ="0.42526" angle="112.1114" ax="0" ay="0" az="1" tx="0.2351" ty="2.9948" tz="1.0878" />
    <Box sX="0.208344" sY="0.02" sZ="0.372979" angle="117.1213" ax="0" ay="0" az="1" tx="0.0228" ty="3.4866" tz="1.1177" />
    <Box sX="0.190717" sY="0.02" sZ="0.378563" angle="104.5775" ax="-0.4175" ay="0.4057" az="0.8131" tx="0.7053" ty="0.8062" tz="-0.908" />
    <Box sX="0.190717" sY="0.02" sZ="0.228685" angle="148.3185" ax="-0.6654" ay="0.6876" az="0.2905" tx="0.7045" ty="0.331" tz="-1.1803" />
    <Box sX="0.190717" sY="0.02" sZ="0.378563" angle="109.4514" ax="-0.418" ay="0.3594" az="0.8343" tx="0.6286" ty="1.588" tz="-0.3355" />
    <Box sX="0.190717" sY="0.02" sZ="0.378563" angle="113.6853" ax="-0.4249" ay="0.3182" az="0.8475" tx="0.4907" ty="2.2284" tz="0.1556" />
    <Box sX="0.190717" sY="0.02" sZ="0.378563" angle="117.4237" ax="-0.421" ay="0.3053" az="0.8541" tx="0.3041" ty="2.8163" tz="0.6254" />
  </Collision>
  <Connectivity>
    <Axel type="2" length="0.8" grabbing="0" startCapped="0" endCapped="0" angle="90" ax="-1" ay="0" az="0" tx="0.4" ty="0.4" tz="1.5196" />
    <Custom2DField type="22" width="2" height="2" angle="90" ax="-1" ay="0" az="0" tx="0" ty="0" tz="1.52">
      29:0,29:0,29:0,
      29:0,15:4:34,29:0,
      29:0,29:0,29:0
    </Custom2DField>
    <Axel type="2" length="0.8" grabbing="0" startCapped="0" endCapped="0" angle="90" ax="-1" ay="0" az="0" tx="-0.4" ty="3.6" tz="1.5196" />
    <Custom2DField type="22" width="2" height="2" angle="90" ax="-1" ay="0" az="0" tx="-0.8" ty="3.2" tz="1.52">
      29:0,29:0,29:0,
      29:0,15:4:34,29:0,
      29:0,29:0,29:0
    </Custom2DField>
    <Axel type="2" length="0.8" grabbing="0" startCapped="0" endCapped="0" angle="0" ax="1" ay="0" az="0" tx="0.4" ty="0" tz="-0.48" />
    <Custom2DField type="22" width="2" height="2" angle="0" ax="1" ay="0" az="0" tx="0" ty="0" tz="-0.88">
      29:0,29:0,29:0,
      29:0,15:4:34,29:0,
      29:0,29:0,29:0
    </Custom2DField>
    <Axel type="2" length="0.8" grabbing="0" startCapped="0" endCapped="0" angle="0" ax="1" ay="0" az="0" tx="0.4" ty="0" tz="0.32" />
    <Custom2DField type="22" width="2" height="2" angle="0" ax="1" ay="0" az="0" tx="0" ty="0" tz="-0.08">
      29:0,29:0,29:0,
      29:0,15:4:34,29:0,
      29:0,29:0,29:0
    </Custom2DField>
  </Connectivity>
  <PhysicsAttributes inertiaTensor="0.098967,0,0,0,0.098967,0,0,0,0.091267" centerOfMass="0,0,-0.4" mass="1" frictionType="0" />
  <Bounding>
    <AABB minX="-0.76" minY="0" minZ="-1.52" maxX="0.76" maxY="3.96" maxZ="1.52" />
  </Bounding>
  <GeometryBounding>
    <AABB minX="-0.76" minY="0" minZ="-1.52" maxX="0.76" maxY="3.96" maxZ="1.52" />
  </GeometryBounding>
</LEGOPrimitive>